pyjob/__init__.py
pyjob/cli.py
pyjob/db.py
pyjob/utils.py
pyjob_cli-0.1.2.dist-info/METADATA
pyjob_cli-0.1.2.dist-info/WHEEL
pyjob_cli-0.1.2.dist-info/entry_points.txt
pyjob_cli-0.1.2.dist-info/top_level.txt
pyjob_cli-0.1.2.dist-info/RECORD
