Metadata-Version: 2.1
Name: pyjob-cli
Version: 0.1.2
Summary: A CLI tool for monitoring Python scripts
Home-page: https://github.com/jtheol/pyjob-cli
Author: jtheol
Author-email: 
Classifier: Programming Language :: Python :: 3
Classifier: License :: OSI Approved :: MIT License
Classifier: Operating System :: OS Independent
Requires-Python: >=3.12
